wujihandpy/_core.cp312-win_amd64.pyd
wujihandpy/_version.py
wujihandpy/__init__.py
wujihandpy/_core/filter.pyi
wujihandpy/_core/logging.pyi
wujihandpy/_core/__init__.pyi
wujihandpy-1.2.0.dist-info/DELVEWHEEL
wujihandpy-1.2.0.dist-info/METADATA
wujihandpy-1.2.0.dist-info/RECORD
wujihandpy-1.2.0.dist-info/WHEEL
wujihandpy-1.2.0.dist-info/licenses/LICENSE
wujihandpy.libs/libusb-1.0-3923377194ccfc94eb937261066315d7.dll
wujihandpy.libs/msvcp140-a4c2229bdc2a2a630acdc095b4d86008.dll
wujihandpy.libs/msvcp140_atomic_wait-eb238a7437cff8f49c01cc67fd035163.dll
