Metadata-Version: 2.2
Name: wujihandpy
Version: 1.2.0
Summary: Python bindings for WujiHandCpp
Author-Email: Zihan Qin <zihanqin2048@gmail.com>
Maintainer-Email: Wuji Technology <support@pan-motor.com>
License: MIT License
Project-URL: homepage, https://github.com/Wuji-Technology-Co-Ltd/wujihandpy
Project-URL: repository, https://github.com/Wuji-Technology-Co-Ltd/wujihandpy
Project-URL: Bug Tracker, https://github.com/Wuji-Technology-Co-Ltd/wujihandpy/issues
Requires-Python: >=3.8
Requires-Dist: numpy
